ldn_serializer/__init__.py
ldn_serializer-0.1.0.dist-info/METADATA
ldn_serializer-0.1.0.dist-info/WHEEL
ldn_serializer-0.1.0.dist-info/top_level.txt
ldn_serializer-0.1.0.dist-info/RECORD
