Metadata-Version: 2.1
Name: ldn-serializer
Version: 0.1.0
Summary: Demo library
Home-page: https://medium-multiply.readthedocs.io/
Author: leinadalien
Author-email: danila.box@tut.by
License: MIT
Platform: UNKNOWN
Classifier: Intended Audience :: Developers
Classifier: License :: OSI Approved :: MIT License
Classifier: Programming Language :: Python
Classifier: Programming Language :: Python :: 3.8
Classifier: Programming Language :: Python :: 3.9
Classifier: Operating System :: OS Independent
